TelegramAdapter/Converter.py
TelegramAdapter/Core.py
TelegramAdapter/__init__.py
erispulse_telegramadapter-3.4.0.dist-info/licenses/LICENSE
erispulse_telegramadapter-3.4.0.dist-info/METADATA
erispulse_telegramadapter-3.4.0.dist-info/WHEEL
erispulse_telegramadapter-3.4.0.dist-info/entry_points.txt
erispulse_telegramadapter-3.4.0.dist-info/top_level.txt
erispulse_telegramadapter-3.4.0.dist-info/RECORD
