Metadata-Version: 2.4
Name: ErisPulse-TelegramAdapter
Version: 3.4.0
Summary: ErisPulse的云湖协议适配模块
Author-email: wsu2059 <wsu2059@qq.com>
License: MIT License
Project-URL: homepage, https://github.com/ErisPulse/ErisPulse-TelegramAdapter
Requires-Python: >=3.9
License-File: LICENSE
Requires-Dist: aiohttp
Requires-Dist: aiohttp-socks
Requires-Dist: certifi
Dynamic: license-file
